src/pycounts-ik/__init__.py
src/pycounts-ik/plotting.py
src/pycounts-ik/pycounts.py
pycounts_ik-0.1.0.dist-info/LICENSE
pycounts_ik-0.1.0.dist-info/WHEEL
pycounts_ik-0.1.0.dist-info/METADATA
pycounts_ik-0.1.0.dist-info/RECORD
