Metadata-Version: 2.1
Name: pycounts-ik
Version: 0.1.0
Summary: 
Author: Ivan Khokhlov
Author-email: khokhlov.ivan@protonmail.com
Requires-Python: >=3.10.0
Classifier: Programming Language :: Python :: 3
Classifier: Programming Language :: Python :: 3.10
Classifier: Programming Language :: Python :: 3.11
Requires-Dist: matplotlib (>=3.6.3)
